rml2shacl/RML.py
rml2shacl/RMLtoShacl.py
rml2shacl/SHACL.py
rml2shacl/__init__.py
rml2shacl/__main__.py
rml2shacl/rml_model.py
rml2shacl/visualize.py
rml2shacl-1.0.0.dist-info/LICENSE
rml2shacl-1.0.0.dist-info/METADATA
rml2shacl-1.0.0.dist-info/WHEEL
rml2shacl-1.0.0.dist-info/RECORD
