Metadata-Version: 2.1
Name: rml2shacl
Version: 1.0.0
Summary: Translates RML into SHACL
Author: Thomas Delva
Author-email: Thomas.Delva@UGent.be
Requires-Python: >=3.9,<4.0
Classifier: Programming Language :: Python :: 3
Classifier: Programming Language :: Python :: 3.9
Classifier: Programming Language :: Python :: 3.10
Classifier: Programming Language :: Python :: 3.11
Classifier: Programming Language :: Python :: 3.12
Classifier: Programming Language :: Python :: 3.13
Requires-Dist: pyshacl (==0.17.2)
Requires-Dist: rdflib (==6.0.2)
Requires-Dist: requests (==2.32.3)
Requires-Dist: shaclgen (==0.2.5.2)
